setup.py
attrgettersetter/__init__.py
attrgettersetter.egg-info/PKG-INFO
attrgettersetter.egg-info/SOURCES.txt
attrgettersetter.egg-info/dependency_links.txt
attrgettersetter.egg-info/entry_points.txt
attrgettersetter.egg-info/not-zip-safe
attrgettersetter.egg-info/top_level.txt