Metadata-Version: 1.0
Name: attrgettersetter
Version: 0.1
Summary: Attribute getter and setter helper tools (useful for attribute.dot.syntax)
Home-page: http://bradjasper.com
Author: Brad Jasper
Author-email: contact@bradjasper.com
License: MIT
Keywords: attr attribute getter setter
Platform: UNKNOWN
